Metadata-Version: 2.1
Name: pokemonPackage2
Version: 0.5
Summary: Practica final Pokemon
Home-page: 
Download-URL: 
Author: Omar
Author-email: xxx@gmail.com
License: MIT
Keywords: get_grupos_pokemon,get_altura_media_grupo,get_peso_medio_grupo
Classifier: Development Status :: 3 - Alpha
Classifier: Intended Audience :: Developers
Classifier: Topic :: Software Development :: Build Tools
Classifier: License :: OSI Approved :: MIT License
Classifier: Programming Language :: Python :: 3
Classifier: Programming Language :: Python :: 3.4
Classifier: Programming Language :: Python :: 3.5
Classifier: Programming Language :: Python :: 3.6
License-File: LICENSE.txt
Requires-Dist: pytest
